moecolor/README.py
moecolor/__init__.py
moecolor/main.py
moecolor/version.py
moecolor-1.0.6.dist-info/LICENSE
moecolor-1.0.6.dist-info/METADATA
moecolor-1.0.6.dist-info/WHEEL
moecolor-1.0.6.dist-info/top_level.txt
moecolor-1.0.6.dist-info/RECORD
