Metadata-Version: 2.1
Name: moecolor
Version: 1.0.6
Summary: Python Libary to print colored and styled text in terminal. Offers color-specific configuration by providing 24bit hex or RGB values as well 256-color mode.
Home-page: https://github.com/mhamdan91/moecolor
Author: mhamdan91 (Hamdan, Muhammad)
Author-email: <mhamdan.dev@gmail.com>
Keywords: python,color,terminal,text,styling,ansi,coloring text,text styling,text formatting,formatting
Classifier: Development Status :: 5 - Production/Stable
Classifier: Intended Audience :: Developers
Classifier: Programming Language :: Python :: 3
Classifier: Operating System :: Unix
Classifier: Operating System :: MacOS :: MacOS X
Classifier: Operating System :: Microsoft :: Windows
Classifier: License :: OSI Approved :: MIT License
License-File: LICENSE
